filter_aggregator/__init__.py
filter_aggregator/filter.py
filter_aggregator-1.1.3.dist-info/licenses/LICENSE
filter_aggregator-1.1.3.dist-info/METADATA
filter_aggregator-1.1.3.dist-info/WHEEL
filter_aggregator-1.1.3.dist-info/top_level.txt
filter_aggregator-1.1.3.dist-info/RECORD
