Metadata-Version: 2.4
Name: filter_aggregator
Version: 1.1.3
License-Expression: Apache-2.0
Classifier: Programming Language :: Python :: 3
Classifier: Programming Language :: Python :: 3.10
Classifier: Programming Language :: Python :: 3.11
Classifier: Programming Language :: Python :: 3.12
Classifier: Programming Language :: Python :: 3.13
Requires-Python: <3.14,>=3.10
License-File: LICENSE
Requires-Dist: openfilter[all]<0.2.0,>=0.1.0
Provides-Extra: dev
Requires-Dist: build==1.2.1; extra == "dev"
Requires-Dist: setuptools==72.2.0; extra == "dev"
Requires-Dist: twine<7,>=6.1.0; extra == "dev"
Requires-Dist: wheel==0.44.0; extra == "dev"
Requires-Dist: pytest==8.3.4; extra == "dev"
Requires-Dist: pytest-cov==6.0.0; extra == "dev"
Dynamic: license-file
